tmgjl_python/__init__.py
tmgjl_python/sound.py
tmgjl_python/sprites.py
tmgjl_python-0.1.0.0.dist-info/METADATA
tmgjl_python-0.1.0.0.dist-info/WHEEL
tmgjl_python-0.1.0.0.dist-info/RECORD
